LICENSE
MANIFEST.in
README.rst
requirements.txt
setup.py
jxltom_kappa.egg-info/PKG-INFO
jxltom_kappa.egg-info/SOURCES.txt
jxltom_kappa.egg-info/dependency_links.txt
jxltom_kappa.egg-info/entry_points.txt
jxltom_kappa.egg-info/requires.txt
jxltom_kappa.egg-info/top_level.txt
jxltom_kappa.egg-info/zip-safe
kappa/__init__.py
kappa/awsclient.py
kappa/context.py
kappa/function.py
kappa/log.py
kappa/policy.py
kappa/restapi.py
kappa/role.py
kappa/event_source/__init__.py
kappa/event_source/base.py
kappa/event_source/cloudwatch.py
kappa/event_source/dynamodb_stream.py
kappa/event_source/kinesis.py
kappa/event_source/s3.py
kappa/event_source/sns.py
kappa/scripts/__init__.py
kappa/scripts/cli.py
samples/cron/_src/simple.py
samples/cron/_tests/test_one.json
samples/kinesis/ProcessKinesisRecords.js
samples/kinesis/config.yml
samples/kinesis/input.json
samples/kinesis/roles.cf
samples/python/_src/dev_config.json
samples/python/_src/prod_config.json
samples/python/_src/requirements.txt
samples/python/_src/simple.py
samples/python/_tests/test_get.json
samples/python/_tests/test_post.json
samples/python/_tests/unit/__init__.py
samples/python/_tests/unit/test_simple.py
samples/s3/config.yml
samples/s3/input.json
samples/s3/roles.cf
samples/s3/examplefolder/CreateThumbnail.js
samples/simple/_src/requirements.txt
samples/simple/_src/simple.py
samples/simple/_tests/test_one.json
samples/sns/input.json
samples/sns/_src/sns.py